pyvap/__init__.py
pyvap/main.py
pyvap/version.py
pyvap-0.1.1.dist-info/DESCRIPTION.rst
pyvap-0.1.1.dist-info/METADATA
pyvap-0.1.1.dist-info/RECORD
pyvap-0.1.1.dist-info/WHEEL
pyvap-0.1.1.dist-info/metadata.json
pyvap-0.1.1.dist-info/top_level.txt
