Metadata-Version: 2.0
Name: pyvap
Version: 0.1.1
Summary: Kinetic model of particle evaporation
Home-page: https://github.com/awbirdsall/pyvap
Author: Adam Birdsall
Author-email: abirdsall@gmail.com
License: MIT
Keywords: kinetics,chemistry,evaporation
Platform: UNKNOWN
Classifier: Development Status :: 3 - Alpha
Classifier: Intended Audience :: Science/Research
Classifier: Topic :: Scientific/Engineering :: Atmospheric Science
Classifier: Topic :: Scientific/Engineering :: Chemistry
Classifier: Topic :: Scientific/Engineering :: Physics
Classifier: License :: OSI Approved :: MIT License
Classifier: Programming Language :: Python :: 2
Classifier: Programming Language :: Python :: 2.7
Classifier: Programming Language :: Python :: 3
Classifier: Programming Language :: Python :: 3.5
Requires-Dist: matplotlib (>=1.5)
Requires-Dist: numpy
Requires-Dist: scipy
